{
    "members": [
        {
            "name": "",
            "address": [
                {
                    "street": "",
                    "city": "",
                    "state": "",
                    "zipcode": ""
                }
                ],
            
            "phoneNumber": "",
            "url": "",
            "memberLevel": "",
            "image": ""
        },
        {
            "name": "",
            "address": [
                {
                    "street": "",
                    "city": "",
                    "state": "",
                    "zipcode": ""
                }
                ],
            
            "phoneNumber": "",
            "url": "",
            "memberLevel": "",
            "image": ""
        },
        {
            "name": "",
            "address": [
                {
                    "street": "",
                    "city": "",
                    "state": "",
                    "zipcode": ""
                }
                ],
            
            "phoneNumber": "",
            "url": "",
            "memberLevel": "",
            "image": ""
        },
        {
            "name": "",
            "address": [
                {
                    "street": "",
                    "city": "",
                    "state": "",
                    "zipcode": ""
                }
                ],
            
            "phoneNumber": "",
            "url": "",
            "memberLevel": "",
            "image": ""
        },
        {
            "name": "",
            "address": [
                {
                    "street": "",
                    "city": "",
                    "state": "",
                    "zipcode": ""
                }
                ],
            
            "phoneNumber": "",
            "url": "",
            "memberLevel": "",
            "image": ""
        },
        {
            "name": "",
            "address": [
                {
                    "street": "",
                    "city": "",
                    "state": "",
                    "zipcode": ""
                }
                ],
            
            "phoneNumber": "",
            "url": "",
            "memberLevel": "",
            "image": ""
        },
        {
            "name": "",
            "address": [
                {
                    "street": "",
                    "city": "",
                    "state": "",
                    "zipcode": ""
                }
                ],
            
            "phoneNumber": "",
            "url": "",
            "memberLevel": "",
            "image": ""
        },
        {
            "name": "",
            "address": [
                {
                    "street": "",
                    "city": "",
                    "state": "",
                    "zipcode": ""
                }
                ],
            
            "phoneNumber": "",
            "url": "",
            "memberLevel": "",
            "image": ""
        }

    ]
}
 